AUTHORS.rst
LICENSE
MANIFEST.in
README.md
setup.cfg
setup.py
django_saml2_auth_signout_redirect/__init__.py
django_saml2_auth_signout_redirect/apps.py
django_saml2_auth_signout_redirect/plugins.py
django_saml2_auth_signout_redirect.egg-info/PKG-INFO
django_saml2_auth_signout_redirect.egg-info/SOURCES.txt
django_saml2_auth_signout_redirect.egg-info/dependency_links.txt
django_saml2_auth_signout_redirect.egg-info/requires.txt
django_saml2_auth_signout_redirect.egg-info/top_level.txt