Metadata-Version: 2.1
Name: django-saml2-auth-signout-redirect
Version: 0.0.8
Summary: Django SAML2 Plugin for URL redirection on Logout (usually to an IdP logout)
Home-page: https://github.com/ambsw/django-saml2-auth-signout-redirect
Author: Clayton Daley
Author-email: technology+saml2_signout_redirect@gmail.com
License: Apache 2.0
Keywords: Django SAML2 Logout Redirection IdP
Platform: UNKNOWN
Classifier: Development Status :: 3 - Alpha
Classifier: Intended Audience :: Developers
Classifier: Topic :: Software Development :: Libraries :: Python Modules
Classifier: License :: OSI Approved :: Apache Software License
Classifier: Framework :: Django :: 1.5
Classifier: Framework :: Django :: 1.6
Classifier: Framework :: Django :: 1.7
Classifier: Framework :: Django :: 1.8
Classifier: Framework :: Django :: 1.9
Classifier: Framework :: Django :: 1.10
Classifier: Programming Language :: Python :: 2
Classifier: Programming Language :: Python :: 2.6
Classifier: Programming Language :: Python :: 2.7
Classifier: Programming Language :: Python :: 3
Classifier: Programming Language :: Python :: 3.3
Classifier: Programming Language :: Python :: 3.4
Classifier: Programming Language :: Python :: 3.5
Classifier: Programming Language :: Python :: 3.6
